{
  "type": "GROUP",
"name": "All Requests",
"path": "",
"pathFormatted": "group_missing-name-b06d1",
"stats": {
    "name": "All Requests",
    "numberOfRequests": {
        "total": 114963,
        "ok": 114963,
        "ko": 0
    },
    "minResponseTime": {
        "total": 0,
        "ok": 0,
        "ko": 0
    },
    "maxResponseTime": {
        "total": 21159,
        "ok": 21159,
        "ko": 0
    },
    "meanResponseTime": {
        "total": 1097,
        "ok": 1097,
        "ko": 0
    },
    "standardDeviation": {
        "total": 2056,
        "ok": 2056,
        "ko": 0
    },
    "percentiles1": {
        "total": 21,
        "ok": 21,
        "ko": 0
    },
    "percentiles2": {
        "total": 1323,
        "ok": 1323,
        "ko": 0
    },
    "percentiles3": {
        "total": 5837,
        "ok": 5837,
        "ko": 0
    },
    "percentiles4": {
        "total": 7772,
        "ok": 7772,
        "ko": 0
    },
    "group1": {
    "name": "t < 800 ms",
    "htmlName": "t < 800 ms",
    "count": 79645,
    "percentage": 69
},
    "group2": {
    "name": "800 ms <= t < 1200 ms",
    "htmlName": "t >= 800 ms <br> t < 1200 ms",
    "count": 4741,
    "percentage": 4
},
    "group3": {
    "name": "t >= 1200 ms",
    "htmlName": "t >= 1200 ms",
    "count": 30577,
    "percentage": 27
},
    "group4": {
    "name": "failed",
    "htmlName": "failed",
    "count": 0,
    "percentage": 0
},
    "meanNumberOfRequestsPerSecond": {
        "total": 520.1945701357466,
        "ok": 520.1945701357466,
        "ko": 0
    }
},
"contents": {
"req_busca-inva-lida-b5618": {
        "type": "REQUEST",
        "name": "busca inválida",
"path": "busca inválida",
"pathFormatted": "req_busca-inva-lida-b5618",
"stats": {
    "name": "busca inválida",
    "numberOfRequests": {
        "total": 4190,
        "ok": 4190,
        "ko": 0
    },
    "minResponseTime": {
        "total": 0,
        "ok": 0,
        "ko": 0
    },
    "maxResponseTime": {
        "total": 8728,
        "ok": 8728,
        "ko": 0
    },
    "meanResponseTime": {
        "total": 1228,
        "ok": 1228,
        "ko": 0
    },
    "standardDeviation": {
        "total": 2086,
        "ok": 2086,
        "ko": 0
    },
    "percentiles1": {
        "total": 12,
        "ok": 12,
        "ko": 0
    },
    "percentiles2": {
        "total": 1981,
        "ok": 1981,
        "ko": 0
    },
    "percentiles3": {
        "total": 5875,
        "ok": 5875,
        "ko": 0
    },
    "percentiles4": {
        "total": 6843,
        "ok": 6843,
        "ko": 0
    },
    "group1": {
    "name": "t < 800 ms",
    "htmlName": "t < 800 ms",
    "count": 2980,
    "percentage": 71
},
    "group2": {
    "name": "800 ms <= t < 1200 ms",
    "htmlName": "t >= 800 ms <br> t < 1200 ms",
    "count": 55,
    "percentage": 1
},
    "group3": {
    "name": "t >= 1200 ms",
    "htmlName": "t >= 1200 ms",
    "count": 1155,
    "percentage": 28
},
    "group4": {
    "name": "failed",
    "htmlName": "failed",
    "count": 0,
    "percentage": 0
},
    "meanNumberOfRequestsPerSecond": {
        "total": 18.959276018099548,
        "ok": 18.959276018099548,
        "ko": 0
    }
}
    },"req_criac-a-o-ce502": {
        "type": "REQUEST",
        "name": "criação",
"path": "criação",
"pathFormatted": "req_criac-a-o-ce502",
"stats": {
    "name": "criação",
    "numberOfRequests": {
        "total": 54625,
        "ok": 54625,
        "ko": 0
    },
    "minResponseTime": {
        "total": 0,
        "ok": 0,
        "ko": 0
    },
    "maxResponseTime": {
        "total": 9317,
        "ok": 9317,
        "ko": 0
    },
    "meanResponseTime": {
        "total": 1470,
        "ok": 1470,
        "ko": 0
    },
    "standardDeviation": {
        "total": 2292,
        "ok": 2292,
        "ko": 0
    },
    "percentiles1": {
        "total": 32,
        "ok": 32,
        "ko": 0
    },
    "percentiles2": {
        "total": 3024,
        "ok": 3024,
        "ko": 0
    },
    "percentiles3": {
        "total": 6180,
        "ok": 6180,
        "ko": 0
    },
    "percentiles4": {
        "total": 7821,
        "ok": 7821,
        "ko": 0
    },
    "group1": {
    "name": "t < 800 ms",
    "htmlName": "t < 800 ms",
    "count": 36599,
    "percentage": 67
},
    "group2": {
    "name": "800 ms <= t < 1200 ms",
    "htmlName": "t >= 800 ms <br> t < 1200 ms",
    "count": 540,
    "percentage": 1
},
    "group3": {
    "name": "t >= 1200 ms",
    "htmlName": "t >= 1200 ms",
    "count": 17486,
    "percentage": 32
},
    "group4": {
    "name": "failed",
    "htmlName": "failed",
    "count": 0,
    "percentage": 0
},
    "meanNumberOfRequestsPerSecond": {
        "total": 247.17194570135746,
        "ok": 247.17194570135746,
        "ko": 0
    }
}
    },"req_busca-va-lida-d7f0d": {
        "type": "REQUEST",
        "name": "busca válida",
"path": "busca válida",
"pathFormatted": "req_busca-va-lida-d7f0d",
"stats": {
    "name": "busca válida",
    "numberOfRequests": {
        "total": 9590,
        "ok": 9590,
        "ko": 0
    },
    "minResponseTime": {
        "total": 1,
        "ok": 1,
        "ko": 0
    },
    "maxResponseTime": {
        "total": 21159,
        "ok": 21159,
        "ko": 0
    },
    "meanResponseTime": {
        "total": 1967,
        "ok": 1967,
        "ko": 0
    },
    "standardDeviation": {
        "total": 3575,
        "ok": 3575,
        "ko": 0
    },
    "percentiles1": {
        "total": 47,
        "ok": 47,
        "ko": 0
    },
    "percentiles2": {
        "total": 3246,
        "ok": 3246,
        "ko": 0
    },
    "percentiles3": {
        "total": 8839,
        "ok": 8839,
        "ko": 0
    },
    "percentiles4": {
        "total": 16276,
        "ok": 16276,
        "ko": 0
    },
    "group1": {
    "name": "t < 800 ms",
    "htmlName": "t < 800 ms",
    "count": 6420,
    "percentage": 67
},
    "group2": {
    "name": "800 ms <= t < 1200 ms",
    "htmlName": "t >= 800 ms <br> t < 1200 ms",
    "count": 132,
    "percentage": 1
},
    "group3": {
    "name": "t >= 1200 ms",
    "htmlName": "t >= 1200 ms",
    "count": 3038,
    "percentage": 32
},
    "group4": {
    "name": "failed",
    "htmlName": "failed",
    "count": 0,
    "percentage": 0
},
    "meanNumberOfRequestsPerSecond": {
        "total": 43.39366515837104,
        "ok": 43.39366515837104,
        "ko": 0
    }
}
    },"req_consulta-5d76b": {
        "type": "REQUEST",
        "name": "consulta",
"path": "consulta",
"pathFormatted": "req_consulta-5d76b",
"stats": {
    "name": "consulta",
    "numberOfRequests": {
        "total": 46558,
        "ok": 46558,
        "ko": 0
    },
    "minResponseTime": {
        "total": 0,
        "ok": 0,
        "ko": 0
    },
    "maxResponseTime": {
        "total": 4908,
        "ok": 4908,
        "ko": 0
    },
    "meanResponseTime": {
        "total": 469,
        "ok": 469,
        "ko": 0
    },
    "standardDeviation": {
        "total": 730,
        "ok": 730,
        "ko": 0
    },
    "percentiles1": {
        "total": 9,
        "ok": 9,
        "ko": 0
    },
    "percentiles2": {
        "total": 1011,
        "ok": 1012,
        "ko": 0
    },
    "percentiles3": {
        "total": 2016,
        "ok": 2016,
        "ko": 0
    },
    "percentiles4": {
        "total": 2487,
        "ok": 2487,
        "ko": 0
    },
    "group1": {
    "name": "t < 800 ms",
    "htmlName": "t < 800 ms",
    "count": 33646,
    "percentage": 72
},
    "group2": {
    "name": "800 ms <= t < 1200 ms",
    "htmlName": "t >= 800 ms <br> t < 1200 ms",
    "count": 4014,
    "percentage": 9
},
    "group3": {
    "name": "t >= 1200 ms",
    "htmlName": "t >= 1200 ms",
    "count": 8898,
    "percentage": 19
},
    "group4": {
    "name": "failed",
    "htmlName": "failed",
    "count": 0,
    "percentage": 0
},
    "meanNumberOfRequestsPerSecond": {
        "total": 210.66968325791856,
        "ok": 210.66968325791856,
        "ko": 0
    }
}
    }
}

}